[{"line":1,"elements":[{"start_timestamp":"2026-01-20T11:57:09.056Z","before":[{"result":{"error_message":"java.lang.NullPointerException: Cannot invoke \"org.openqa.selenium.WebDriver.findElement(org.openqa.selenium.By)\" because \"this.driver\" is null\r\n\tat QA_Automation.Practice.pages.LoginPage.<init>(LoginPage.java:13)\r\n\tat QA_Automation.Practice.stepdefinitions.TestStory1.setUp(TestStory1.java:42)\r\n","duration":120241189300,"status":"failed"},"match":{"location":"QA_Automation.Practice.stepdefinitions.TestStory1.setUp()"}}],"line":5,"name":"Full Registration & Deletion","description":"","id":"user-account-management-on-automation-exercise-website;full-registration-&-deletion","after":[{"result":{"duration":1035248900,"status":"passed"},"match":{"location":"QA_Automation.Practice.stepdefinitions.TestStory1.tearDown()"}}],"type":"scenario","keyword":"Scenario","steps":[{"result":{"duration":1000400,"status":"skipped"},"line":6,"name":"Launch browser and go to 'http://automationexercise.com'","match":{"arguments":[{"val":"'http://automationexercise.com'","offset":25}],"location":"QA_Automation.Practice.stepdefinitions.TestStory1.i_launch_the_browser(java.lang.String)"},"keyword":"Given "},{"result":{"status":"skipped"},"line":7,"name":"I verify that home page is visible successfully","match":{"location":"QA_Automation.Practice.stepdefinitions.TestStory1.i_verify_home_page_visible()"},"keyword":"Then "},{"result":{"status":"skipped"},"line":8,"name":"I click on Signup_Login button","match":{"location":"QA_Automation.Practice.stepdefinitions.TestStory1.i_click_on_button()"},"keyword":"When "},{"result":{"status":"skipped"},"line":9,"name":"I verify that 'New User Signup' text is displayed on the page","match":{"arguments":[{"val":"'New User Signup'","offset":14}],"location":"QA_Automation.Practice.stepdefinitions.TestStory1.i_verify_that_is_visible(java.lang.String)"},"keyword":"Then "},{"result":{"status":"skipped"},"line":10,"name":"Enter Name and Email address and click 'Signup'","match":{"location":"QA_Automation.Practice.stepdefinitions.TestStory1.i_enter_name_and_email()"},"keyword":"And "}]}],"name":"User Account Management on Automation Exercise Website","description":"","id":"user-account-management-on-automation-exercise-website","keyword":"Feature","uri":"file:src/test/resources/features/TestStory1.feature","tags":[]}]